{
  "scores": [
    {
      "id": 0,
      "player1": 0,
      "player2": 0,
      "winner": ""
    },
    {
      "id": 1,
      "player1": 10,
      "player2": 0,
      "winner": "PLAYER 1"
    },
    {
      "id": "4a414b6e-7fce-4505-afa1-ac29625fc24c",
      "player1": 4,
      "player2": 0,
      "winner": "PLAYER 1"
    },
    {
      "id": "5d8b8039-1c2d-4fdc-8296-c2ffcd6dd08f",
      "player1": 4,
      "player2": 0,
      "winner": "PLAYER 1"
    },
    {
      "id": "ccc541d2-3ead-4b83-b2aa-650315276fc4",
      "player1": 4,
      "player2": 0,
      "winner": "PLAYER 1"
    },
    {
      "id": "5617fcba-cd20-4134-bf79-34e4ef76c699",
      "player1": 4,
      "player2": 0,
      "winner": "PLAYER 1"
    },
    {
      "id": "29c791a4-7581-468c-895f-507d93f97a64",
      "player1": 4,
      "player2": 0,
      "winner": "PLAYER 1"
    },
    {
      "id": "28fcdb99-14a8-4c94-a8b0-7e636f72ff9e",
      "player1": 4,
      "player2": 0,
      "winner": "PLAYER 1"
    },
    {
      "id": "94e52bb7-714c-445f-aad0-27d954ae23d3",
      "player1": 3,
      "player2": 0,
      "winner": "PLAYER 1"
    },
    {
      "id": "268052de-8aec-47ec-9417-07e3ed291fca",
      "player1": 385,
      "player2": 0,
      "winner": "PLAYER 1"
    },
    {
      "id": "498b05c2-7218-42f8-8f90-b7d9f4b50c65",
      "player1": 1,
      "player2": 0,
      "winner": "PLAYER 1"
    },
    {
      "id": "031a3360-bf4b-425d-a394-a6c23f335f1e",
      "player1": 4,
      "player2": 0,
      "winner": "PLAYER 1"
    },
    {
      "id": "6420210b-585b-4b14-b0db-74cb3752ad4a",
      "player1": 3,
      "player2": 0,
      "winner": "PLAYER 1"
    },
    {
      "id": "68f685ef-f335-4de7-bd91-a03189f85cd4",
      "player1": 4,
      "player2": 0,
      "winner": "PLAYER 1"
    },
    {
      "id": "815e796d-0765-4d9a-bc4e-be98b9f1a739",
      "player1": 4,
      "player2": 0,
      "winner": "PLAYER 1"
    },
    {
      "id": "d94d62e1-59d1-45e4-a5a3-07f70c392418",
      "player1": 4,
      "player2": 0,
      "winner": "PLAYER 1"
    },
    {
      "id": "7c14beb9-eb65-4982-bd3b-c84e514e0c43",
      "player1": 4,
      "player2": 0,
      "winner": "PLAYER 1"
    },
    {
      "id": "a4e37056-58a5-4d7e-b862-4f0c9f23af11",
      "player1": 4,
      "player2": 0,
      "winner": "PLAYER 1"
    },
    {
      "id": "62c541b9-f6f5-4fc2-99f5-99155f27da8f",
      "player1": 4,
      "player2": 0,
      "winner": "PLAYER 1"
    },
    {
      "id": "c9e0700f-691f-4f75-bab8-618039f2cff6",
      "player1": 4,
      "player2": 0,
      "winner": "PLAYER 1"
    },
    {
      "id": "79078a31-6436-4aee-a99c-b5ffb72b64a3",
      "player1": 4,
      "player2": 0,
      "winner": "PLAYER 1"
    },
    {
      "id": "7593fee7-ab04-4fa5-a8b0-85e7c6464348",
      "player1": 5,
      "player2": 0,
      "winner": "PLAYER 1"
    },
    {
      "id": "7cb6ae4c-39d8-4461-85ae-41b6506dbbdd",
      "player1": 5,
      "player2": 0,
      "winner": "PLAYER 1"
    },
    {
      "id": "57e702de-302a-4734-bb9e-4e8720fca792",
      "player1": 4,
      "player2": 0,
      "winner": "PLAYER 1"
    },
    {
      "id": "4411bbf5-832a-4381-9609-5eccf3e8ffad",
      "player1": 5,
      "player2": 0,
      "winner": "PLAYER 1"
    },
    {
      "id": "d597d8d9-03dd-4a44-9fdf-35bdd74ada3c",
      "player1": 15,
      "player2": 0,
      "winner": "PLAYER 1"
    },
    {
      "id": "740b1750-f06c-46cb-a0f6-8981caed38c3",
      "player1": 15,
      "player2": 0,
      "winner": "PLAYER 1"
    },
    {
      "id": "bcce8737-6501-4516-a9b2-23f786c4e2db",
      "player1": 6,
      "player2": 8,
      "winner": "PLAYER2"
    },
    {
      "id": "f1258be4-0361-4690-8a5c-f6637cb9777e",
      "player1": 7,
      "player2": 0,
      "winner": "PLAYER 1"
    },
    {
      "id": "3d25c909-36a9-46d3-887a-ac96c1a53c63",
      "player1": 0,
      "player2": 6,
      "winner": "PLAYER2"
    },
    {
      "id": "f3cf294f-ac6b-43c7-ac3f-262196f25ed2",
      "player1": 2,
      "player2": 12,
      "winner": "PLAYER2"
    },
    {
      "id": "3ebd351a-e6e0-4df1-af8d-6a067b483bbb",
      "player1": 4,
      "player2": 0,
      "winner": "PLAYER 1"
    },
    {
      "id": "63e855d0-2d7a-463e-ab6d-027cea8f6f52",
      "player1": 15,
      "player2": 0,
      "winner": "PLAYER 1"
    }
  ],
  "livescore": [
    {
      "id": 0,
      "player1": 0,
      "player2": 0
    },
    {
      "id": "720c0165-5a21-4bf6-b94e-5456168a53eb",
      "player1": 20,
      "player2": 0
    },
    {
      "id": "1c1af9d6-ecee-4102-8477-e0b7346fe342",
      "player1": 1,
      "player2": 0
    },
    {
      "id": "82aaa3f4-27af-400c-8dd8-4bd549f6289b",
      "player1": 1,
      "player2": 0
    },
    {
      "id": "239907b4-65b0-4a50-b46c-df5d12a245f3",
      "player1": 1,
      "player2": 0
    },
    {
      "id": "8ef682e0-05fc-4145-843e-2c99370d45ba",
      "player1": 1,
      "player2": 0
    },
    {
      "id": 17,
      "player1": 4,
      "player2": 0
    },
    {
      "id": 18,
      "player1": 5,
      "player2": 0
    },
    {
      "id": 19,
      "player1": 6,
      "player2": 0
    },
    {
      "id": 20,
      "player1": 7,
      "player2": 0
    },
    {
      "id": 21,
      "player1": 8,
      "player2": 0
    },
    {
      "id": 22,
      "player1": 9,
      "player2": 0
    },
    {
      "id": "855ee690-6d72-4ee3-a2be-c0b386d9aa0a",
      "player1": 1,
      "player2": 0
    },
    {
      "id": "4b8a74d1-f945-497c-a719-1333f2940767",
      "player1": 1,
      "player2": 0
    },
    {
      "id": "acb9b2be-577f-4a36-9a59-cb7b81ab18f8",
      "player1": 1,
      "player2": 0
    },
    {
      "id": 23,
      "player1": 10,
      "player2": 0
    },
    {
      "id": "04f0a784-174f-446e-9cd0-b87c574cdf89",
      "player1": 1,
      "player2": 0
    },
    {
      "id": "04a1b180-9bf1-46ec-af6b-e94574cad0dd",
      "player1": 1,
      "player2": 0
    },
    {
      "id": "d11117a4-2a82-4108-a494-6926a30b96e3",
      "player1": 1,
      "player2": 0
    },
    {
      "id": "475704dd-a690-4b7b-b170-e0a8f3f46815",
      "player1": 1,
      "player2": 0
    },
    {
      "id": "5a1a9a24-3ec3-4066-bf95-b9f10a0eac61",
      "player1": 1,
      "player2": 0
    },
    {
      "id": "97894f68-de7d-4e78-b2c7-ebb738db763c",
      "player1": 1,
      "player2": 0
    },
    {
      "id": "6741eaad-a894-4ad5-bec4-09bfdedfc864",
      "player1": 1,
      "player2": 0
    },
    {
      "id": "de58384a-b97b-44af-b931-39c63c1ab89f",
      "player1": 1,
      "player2": 0
    },
    {
      "id": "1dc41efa-1e60-40ca-8169-98b628285bf1",
      "player1": 1,
      "player2": 0
    },
    {
      "id": "301a1d89-e540-4a5a-a2ee-84e38de73c5f",
      "player1": 1,
      "player2": 0
    },
    {
      "id": "7e18f050-8e28-4a1d-9cc1-5d33862c2fc9",
      "player1": 1,
      "player2": 0
    },
    {
      "id": "286cf3f1-7b7f-4350-8db1-c23178ad2ce8",
      "player1": 1,
      "player2": 0
    },
    {
      "id": "5f5af616-8938-4fa8-aa21-a7af7cd27b8c",
      "player1": 0,
      "player2": 1
    },
    {
      "id": "ae897ed8-7b78-4e70-91a9-ee1ea0c4abee",
      "player1": 1,
      "player2": 0
    },
    {
      "id": "dcce66e0-feec-4ef3-b6a3-3e029b3def0b",
      "player1": 1,
      "player2": 0
    },
    {
      "id": "aaeeaa7e-d96d-4156-bda7-52c2b0581927",
      "player1": 1,
      "player2": 0
    },
    {
      "id": "697eb3fe-d188-4af2-bf0d-a90dbc6270e8",
      "player1": 0,
      "player2": 1
    },
    {
      "id": "488a1429-a913-4570-8280-23761c96d6fc",
      "player1": 1,
      "player2": 0
    },
    {
      "id": "c22925a2-2896-44f3-b629-72dc20acdfec",
      "player1": 1,
      "player2": 0
    },
    {
      "id": "7fa5bd8b-bf4f-485a-b111-bb7901555e8b",
      "player1": 1,
      "player2": 0
    },
    {
      "id": "893790b5-1e56-46ab-a9ff-890df5917529",
      "player1": 1,
      "player2": 0
    },
    {
      "id": "610d373a-983e-4258-9483-2890eb9caa39",
      "player1": 1,
      "player2": 0
    },
    {
      "id": "eed9ec8e-4fdf-4750-a8c0-aa885187de0f",
      "player1": 1,
      "player2": 0
    }
  ]
}